asyncframes/__init__.py
asyncframes/asyncio_eventloop.py
asyncframes/glib_eventloop.py
asyncframes/pyqt5_eventloop.py
asyncframes-2.2.0.dist-info/LICENSE
asyncframes-2.2.0.dist-info/METADATA
asyncframes-2.2.0.dist-info/WHEEL
asyncframes-2.2.0.dist-info/top_level.txt
asyncframes-2.2.0.dist-info/RECORD
