Metadata-Version: 2.1
Name: asyncframes
Version: 2.2.0
Summary: Parallel programming for software engineers
Home-page: https://github.com/RcSepp/asyncframes
Author: Sebastian Klaassen
Author-email: rcsepp@hotmail.com
License: MIT
Platform: UNKNOWN
Classifier: Development Status :: 5 - Production/Stable
Classifier: Intended Audience :: Developers
Classifier: License :: OSI Approved :: MIT License
Classifier: Natural Language :: English
Classifier: Operating System :: OS Independent
Classifier: Programming Language :: Python :: 3
Classifier: Topic :: Software Development :: Libraries :: Application Frameworks
Requires-Python: >=3.5
